cvbiasmitigation/__init__.py
cvbiasmitigation/md.py
cvbiasmitigation/suggest.py
cvbiasmitigation/data/rfw.csv
cvbiasmitigation-0.0.16.dist-info/METADATA
cvbiasmitigation-0.0.16.dist-info/WHEEL
cvbiasmitigation-0.0.16.dist-info/top_level.txt
cvbiasmitigation-0.0.16.dist-info/RECORD
