Metadata-Version: 2.4
Name: cvbiasmitigation
Version: 0.0.16
Summary: A package for discovering biases and suggesting mitigation approaches
Home-page: https://github.com/gsarridis/
Author: Ioannis Sarridis
Author-email: gsarridis@iti.gr
Classifier: Programming Language :: Python :: 3
Classifier: License :: OSI Approved :: Apache Software License
Classifier: Operating System :: OS Independent
Requires-Python: >=3.6
Requires-Dist: scipy
Requires-Dist: pandas
Requires-Dist: matplotlib
Requires-Dist: seaborn
Requires-Dist: numpy>=2
Dynamic: author
Dynamic: author-email
Dynamic: classifier
Dynamic: description
Dynamic: description-content-type
Dynamic: home-page
Dynamic: requires-dist
Dynamic: requires-python
Dynamic: summary
